clicz/__init__.py
clicz-0.0.3.dist-info/LICENSE
clicz-0.0.3.dist-info/METADATA
clicz-0.0.3.dist-info/WHEEL
clicz-0.0.3.dist-info/RECORD
