Metadata-Version: 2.1
Name: clicz
Version: 0.0.3
Summary: 
Author: Mo Balaa
Author-email: balaa@fractalnetworks.co
Requires-Python: >=3.10,<4.0
Classifier: Programming Language :: Python :: 3
Classifier: Programming Language :: Python :: 3.10
Classifier: Programming Language :: Python :: 3.11
Classifier: Programming Language :: Python :: 3.12
Provides-Extra: dev
Requires-Dist: pytest (>=7.4.3,<8.0.0) ; extra == "dev"
Requires-Dist: pyyaml (>=6.0.1,<7.0.0)
